LICENSE
MANIFEST.in
README.rst
setup.py
smartframes/SmartFrames.py
smartframes/__init__.py
smartframes.egg-info/PKG-INFO
smartframes.egg-info/SOURCES.txt
smartframes.egg-info/dependency_links.txt
smartframes.egg-info/top_level.txt