Metadata-Version: 1.1
Name: smartframes
Version: 1.0.1
Summary: Enhanced Python Dataframes for Spark/PySpark
Home-page: https://github.com/dondrake/smartframes
Author: Don Drake
Author-email: don@drakeconsulting.com
License: Apache
Keywords: Spark PySpark DataFrame
Platform: UNKNOWN
Classifier: Development Status :: 5 - Production/Stable
Classifier: Intended Audience :: Developers
Classifier: Topic :: Utilities
Classifier: License :: OSI Approved :: Apache Software License
Classifier: Programming Language :: Python :: 2
Classifier: Programming Language :: Python :: 2.6
Classifier: Programming Language :: Python :: 2.7
Classifier: Programming Language :: Python :: 3
Classifier: Programming Language :: Python :: 3.2
Classifier: Programming Language :: Python :: 3.3
Classifier: Programming Language :: Python :: 3.4
